cypress_db/__init__.py
cypress_db/__main__.py
cypress_db/cmd.py
cypress_db/settings.py
cypress_django-0.1.0.dist-info/LICENSE
cypress_django-0.1.0.dist-info/METADATA
cypress_django-0.1.0.dist-info/WHEEL
cypress_django-0.1.0.dist-info/entry_points.txt
cypress_django-0.1.0.dist-info/top_level.txt
cypress_django-0.1.0.dist-info/RECORD
