Metadata-Version: 2.1
Name: cypress-django
Version: 0.1.0
Summary: Cypress DB helper command line script
Home-page: https://github.com/QuickRelease/cypress-django.git
Author: David Vaughan
Author-email: david.vaughan@quickrelease.co.uk
Maintainer: Quick Release (Automotive) Ltd.
License: MIT
Keywords: cypress django test
Platform: UNKNOWN
Classifier: Programming Language :: Python :: 3
Classifier: Framework :: Django :: 1.11
Classifier: Framework :: Django :: 2.0
Classifier: Framework :: Django :: 2.1
Classifier: Framework :: Django :: 2.2
Classifier: Framework :: Django :: 3.0
Classifier: Framework :: Django :: 3.1
Classifier: Framework :: Django :: 3.2
Classifier: License :: OSI Approved :: MIT License
Classifier: Intended Audience :: Developers
Classifier: Operating System :: OS Independent
Requires-Dist: Django (>=1.11)
